LICENSE
MANIFEST.in
README.rst
requirements.txt
setup.py
spam_lists/__init__.py
spam_lists/clients.py
spam_lists/compat.py
spam_lists/composites.py
spam_lists/exceptions.py
spam_lists/host_collections.py
spam_lists/host_list.py
spam_lists/structures.py
spam_lists/validation.py
spam_lists.egg-info/PKG-INFO
spam_lists.egg-info/SOURCES.txt
spam_lists.egg-info/dependency_links.txt
spam_lists.egg-info/requires.txt
spam_lists.egg-info/top_level.txt
test/__init__.py
test/compat.py
test/integration/__init__.py
test/integration/test_clients.py
test/unit/__init__.py
test/unit/common_definitions.py
test/unit/test_clients.py
test/unit/test_composites.py
test/unit/test_host_collections.py
test/unit/test_host_list.py
test/unit/test_structures.py
test/unit/test_validation.py