Metadata-Version: 1.1
Name: spam-lists
Version: 1.0.0
Summary: Web address blacklist/whitelist library for Python
Home-page: https://github.com/piotr-rusin/spam-lists
Author: Piotr Rusin
Author-email: piotr.rusin88@gmail.com
License: MIT
Keywords: spam dnsbl surbl google-safe-browsing-api spamhaus whitelist blacklist
Platform: UNKNOWN
Classifier: Development Status :: 5 - Production/Stable
Classifier: Intended Audience :: Developers
Classifier: Natural Language :: English
Classifier: License :: OSI Approved :: MIT License
Classifier: Programming Language :: Python :: 2.7
Classifier: Programming Language :: Python :: 3.4
